SurikovDB/Block.py
SurikovDB/BlockStorage.py
SurikovDB/CLISurikovDB.py
SurikovDB/DBMS.py
SurikovDB/DataBase.py
SurikovDB/DataBaseCommand.py
SurikovDB/DataBaseStorage.py
SurikovDB/Expression.py
SurikovDB/JSONQLException.py
SurikovDB/JSONQLParser.py
SurikovDB/RowSet.py
SurikovDB/Transaction.py
SurikovDB/__init__.py
SurikovDB/constants.py
SurikovDB/test.py
SurikovDB/test2.py
SurikovDB/DDL/Column.py
SurikovDB/DDL/CreateTable.py
SurikovDB/DDL/DropTable.py
SurikovDB/DDL/TableMetaData.py
SurikovDB/DDL/__init__.py
SurikovDB/DML/Delete.py
SurikovDB/DML/Insert.py
SurikovDB/DML/InsertRow.py
SurikovDB/DML/InsertRows.py
SurikovDB/DML/Select.py
SurikovDB/DML/Update.py
SurikovDB/DML/__init__.py
SurikovDB/Server/__init__.py
SurikovDB/Server/server.py
SurikovDB/folder1/__init__.py
SurikovDB/folder1/test2.py
SurikovDB-1.0.0.dist-info/METADATA
SurikovDB-1.0.0.dist-info/WHEEL
SurikovDB-1.0.0.dist-info/entry_points.txt
SurikovDB-1.0.0.dist-info/top_level.txt
SurikovDB-1.0.0.dist-info/RECORD
